google/cloud/managedkafka/__init__.py
google/cloud/managedkafka/gapic_version.py
google/cloud/managedkafka/py.typed
google/cloud/managedkafka_v1/__init__.py
google/cloud/managedkafka_v1/gapic_metadata.json
google/cloud/managedkafka_v1/gapic_version.py
google/cloud/managedkafka_v1/py.typed
google/cloud/managedkafka_v1/services/__init__.py
google/cloud/managedkafka_v1/services/managed_kafka/__init__.py
google/cloud/managedkafka_v1/services/managed_kafka/async_client.py
google/cloud/managedkafka_v1/services/managed_kafka/client.py
google/cloud/managedkafka_v1/services/managed_kafka/pagers.py
google/cloud/managedkafka_v1/services/managed_kafka/transports/__init__.py
google/cloud/managedkafka_v1/services/managed_kafka/transports/base.py
google/cloud/managedkafka_v1/services/managed_kafka/transports/grpc.py
google/cloud/managedkafka_v1/services/managed_kafka/transports/grpc_asyncio.py
google/cloud/managedkafka_v1/services/managed_kafka/transports/rest.py
google/cloud/managedkafka_v1/services/managed_kafka/transports/rest_base.py
google/cloud/managedkafka_v1/services/managed_kafka_connect/__init__.py
google/cloud/managedkafka_v1/services/managed_kafka_connect/async_client.py
google/cloud/managedkafka_v1/services/managed_kafka_connect/client.py
google/cloud/managedkafka_v1/services/managed_kafka_connect/pagers.py
google/cloud/managedkafka_v1/services/managed_kafka_connect/transports/__init__.py
google/cloud/managedkafka_v1/services/managed_kafka_connect/transports/base.py
google/cloud/managedkafka_v1/services/managed_kafka_connect/transports/grpc.py
google/cloud/managedkafka_v1/services/managed_kafka_connect/transports/grpc_asyncio.py
google/cloud/managedkafka_v1/services/managed_kafka_connect/transports/rest.py
google/cloud/managedkafka_v1/services/managed_kafka_connect/transports/rest_base.py
google/cloud/managedkafka_v1/types/__init__.py
google/cloud/managedkafka_v1/types/managed_kafka.py
google/cloud/managedkafka_v1/types/managed_kafka_connect.py
google_cloud_managedkafka-0.1.11.dist-info/LICENSE
google_cloud_managedkafka-0.1.11.dist-info/METADATA
google_cloud_managedkafka-0.1.11.dist-info/WHEEL
google_cloud_managedkafka-0.1.11.dist-info/top_level.txt
google_cloud_managedkafka-0.1.11.dist-info/RECORD
